unionfind.py
pyunionfind-1.0.0.dist-info/LICENSE
pyunionfind-1.0.0.dist-info/METADATA
pyunionfind-1.0.0.dist-info/WHEEL
pyunionfind-1.0.0.dist-info/top_level.txt
pyunionfind-1.0.0.dist-info/RECORD
