Metadata-Version: 2.1
Name: pyunionfind
Version: 1.0.0
Summary: A union-find disjoint sets data structure
Home-page: https://github.com/hagai-helman/unionfind
Author: Debajyoti Nandi, Hagai Helman Tov
Maintainer: Hagai Helman Tov
Maintainer-email: hagai.helman@gmail.com
License: 'MIT',
Platform: UNKNOWN
Classifier: Development Status :: 5 - Production/Stable
Classifier: License :: OSI Approved :: MIT License
Classifier: Intended Audience :: Developers
Classifier: Intended Audience :: Science/Research
Classifier: Programming Language :: Python
Classifier: Programming Language :: Python :: 2
Classifier: Programming Language :: Python :: 3
Classifier: Topic :: Scientific/Engineering
Classifier: Topic :: Scientific/Engineering :: Mathematics
License-File: LICENSE
